MANIFEST.in
README.rst
setup.cfg
setup.py
examples/clienttest.py
examples/handler.py
examples/runserver.py
examples/appearance/skins/simple/service.css
examples/appearance/skins/simple/service.template
examples/files/flower01.jpg
examples/files/flower02.jpg
examples/files/socket.h
examples/services/albums.pickle
examples/services/albumservice.py
examples/services/calculator.py
examples/services/shopservice.py
examples/services/taskservice.py
examples/services/transferservice.py
scripts/ladon-3.6-ctl
scripts/ladon-ctl
src/ladon/__init__.py
src/ladon/compat.py
src/ladon.egg-info/PKG-INFO
src/ladon.egg-info/SOURCES.txt
src/ladon.egg-info/dependency_links.txt
src/ladon.egg-info/not-zip-safe
src/ladon.egg-info/requires.txt
src/ladon.egg-info/top_level.txt
src/ladon/clients/__init__.py
src/ladon/clients/jsonwsp.py
src/ladon/exceptions/__init__.py
src/ladon/exceptions/base.py
src/ladon/exceptions/dispatcher.py
src/ladon/exceptions/interfaces.py
src/ladon/exceptions/ladonizer.py
src/ladon/exceptions/service.py
src/ladon/exceptions/types.py
src/ladon/interfaces/__init__.py
src/ladon/interfaces/base.py
src/ladon/interfaces/jsonrpc10.py
src/ladon/interfaces/jsonwsp.py
src/ladon/interfaces/soap.py
src/ladon/interfaces/soap11.py
src/ladon/interfaces/soap_old.py
src/ladon/interfaces/xmlrpc.py
src/ladon/ladonizer/__init__.py
src/ladon/ladonizer/collection.py
src/ladon/ladonizer/decorator.py
src/ladon/resources/skins/bluebox/service.template
src/ladon/resources/skins/bluebox/css/service-ui.css
src/ladon/resources/skins/bluebox/css/service.css
src/ladon/resources/skins/bluebox/images/spinner.gif
src/ladon/resources/skins/bluebox/js/jquery.min.js
src/ladon/resources/skins/bluebox/js/jsonwspclient.js
src/ladon/resources/skins/bluebox/js/service-ui.js
src/ladon/resources/skins/rounded/catalog.template
src/ladon/resources/skins/rounded/service.template
src/ladon/resources/skins/rounded/css/catalog.css
src/ladon/resources/skins/rounded/css/service.css
src/ladon/server/__init__.py
src/ladon/server/customresponse.py
src/ladon/server/dispatcher.py
src/ladon/server/wsgi.py
src/ladon/server/wsgi_application.py
src/ladon/server/default/__init__.py
src/ladon/server/default/css.py
