Metadata-Version: 1.2
Name: ladon
Version: 1.0.5
Summary: Serve your python methods to several web service interfaces at once, including JSON-WSP, SOAP and JSON-RPC.
Home-page: https://bitbucket.org/jakobsg/ladon
Author: Jakob Simon-Gaarde
Author-email: jakob@simon-gaarde.dk
Maintainer: Jakob Simon-Gaarde
Maintainer-email: jakob@simon-gaarde.dk
License: LGPL3
Keywords: ladonize,soap,json,shell,rpc,wsgi
Platform: UNKNOWN
Classifier: Programming Language :: Python
Classifier: Programming Language :: Python :: 2
Classifier: Programming Language :: Python :: 3
Classifier: Operating System :: OS Independent
Classifier: Natural Language :: English
Classifier: Intended Audience :: Developers
Classifier: Topic :: Internet :: WWW/HTTP :: WSGI :: Server
Classifier: Topic :: Internet :: WWW/HTTP :: WSGI :: Application
Requires: jinja2
Requires: sphinx
Requires: sphinx_bootstrap_theme
Requires: chardet
Requires: python_memcached
Requires: redis
Provides: ladon
